LICENSE
MANIFEST.in
README.md
setup.py
src/__init__.py
src/melody/__init__.py
src/melody/inputs.py
src/melody/main.py
src/melody/search.py
src/melody.egg-info/PKG-INFO
src/melody.egg-info/SOURCES.txt
src/melody.egg-info/dependency_links.txt
src/melody.egg-info/requires.txt
src/melody.egg-info/top_level.txt
src/melody/tests/inputs/choice_test.py
src/melody/tests/inputs/create_input_test.py
src/melody/tests/inputs/fixed_test.py
src/melody/tests/inputs/floatrange_test.py
src/melody/tests/inputs/input_test.py
src/melody/tests/inputs/intrange_test.py
src/melody/tests/inputs/subsets_test.py
src/melody/tests/inputs/switch_test.py
src/melody/tests/main/melody_test.py
src/melody/tests/search/bruteforce_test.py
src/melody/tests/search/searchmethod_test.py