Metadata-Version: 1.1
Name: melody
Version: 0.1.0
Summary: lightweight python parameter search tool
Home-page: https://github.com/rupertford/melody
Author: Rupert Ford
Author-email: rupert.ford@stfc.ac.uk
License: OSI Approved :: BSD 3-Clause License
Platform: UNKNOWN
Classifier: Development Status :: 3 - Alpha
Classifier: Environment :: Console
Classifier: Intended Audience :: Developers
Classifier: Intended Audience :: Science/Research
Classifier: Natural Language :: English
Classifier: Programming Language :: Python :: 2.7
Classifier: Topic :: Scientific/Engineering
Classifier: Topic :: Software Development
Classifier: Topic :: Utilities
Classifier: Operating System :: POSIX
Classifier: Operating System :: Unix
Classifier: Operating System :: MacOS
